create_dash_app/__init__.py
create_dash_app/__main__.py
create_dash_app/generators.py
create_dash_app/main.py
create_dash_app/templates/__init__.py
create_dash_app/templates/assets.py
create_dash_app/templates/callbacks.py
create_dash_app/templates/components.py
create_dash_app/templates/keys.py
create_dash_app/templates/root.py
create_dash_app/templates/assets/dash.min.css
create_dash_app/templates/assets/dbc.min.css
create_dash_app-0.1.2.dist-info/LICENSE
create_dash_app-0.1.2.dist-info/METADATA
create_dash_app-0.1.2.dist-info/WHEEL
create_dash_app-0.1.2.dist-info/entry_points.txt
create_dash_app-0.1.2.dist-info/top_level.txt
create_dash_app-0.1.2.dist-info/RECORD
