Metadata-Version: 2.1
Name: create-dash-app
Version: 0.1.2
Summary: Generate boilerplate code for plotly Dash apps
Home-page: https://github.com/eliwoods/create-dash-app
Author: Eli Woods
License: UNKNOWN
Project-URL: Bug Tracker, https://github.com/eliwoods/create-dash-app/issues
Platform: UNKNOWN
Classifier: Programming Language :: Python :: 3
Classifier: License :: OSI Approved :: BSD License
Classifier: Operating System :: OS Independent
Requires-Python: >=3.6
License-File: LICENSE
Requires-Dist: Flask-Caching (>=1.10.1)
Requires-Dist: dash (>=2.1.0)
Requires-Dist: dash-bootstrap-components (>=1.0.2)
Requires-Dist: gunicorn (>=20.1.0)
Requires-Dist: rich (>=11.1.0)
